extencli/__init__.py
extencli/group.py
extencli/py.typed
extencli-0.1.2.dist-info/licenses/LICENSE
extencli-0.1.2.dist-info/METADATA
extencli-0.1.2.dist-info/WHEEL
extencli-0.1.2.dist-info/top_level.txt
extencli-0.1.2.dist-info/RECORD
